.gitignore
LICENSE.txt
README.rst
bump.sh
html4css1.css
index.html
make-index
math.css
setup.cfg
setup.py
upload.bat
windows.bat
addcourse/__init__.py
addcourse/__main__.py
addcourse/addpage.py
addcourse/browser.py
addcourse/class_numbers.py
addcourse/course_adder.py
addcourse/error.py
addcourse/main.py
addcourse/preview.py
addcourse/version.py
uwaterloo_addcourse.egg-info/PKG-INFO
uwaterloo_addcourse.egg-info/SOURCES.txt
uwaterloo_addcourse.egg-info/dependency_links.txt
uwaterloo_addcourse.egg-info/entry_points.txt
uwaterloo_addcourse.egg-info/requires.txt
uwaterloo_addcourse.egg-info/top_level.txt