Metadata-Version: 1.1
Name: uwaterloo-addcourse
Version: 1.2.1
Summary: Package for easily adding a course on UWaterloo's QUEST.
Home-page: https://github.com/kcolford/uwaterloo-addcourse
Author: Kieran Colford
Author-email: colfordk@gmail.com
License: GPLv3+
Keywords: uwaterloo,addcourse
Platform: Any
Classifier: Development Status :: 5 - Production/Stable
Classifier: Environment :: Console
Classifier: Intended Audience :: End Users/Desktop
Classifier: License :: OSI Approved :: GNU General Public License v3 or later (GPLv3+)
Classifier: Natural Language :: English
Classifier: Operating System :: OS Independent
Classifier: Programming Language :: Python
